git_utils_py/Artifacts.py
git_utils_py/Clone.py
git_utils_py/File.py
git_utils_py/__init__.py
git_utils_py-0.0.7.dist-info/METADATA
git_utils_py-0.0.7.dist-info/WHEEL
git_utils_py-0.0.7.dist-info/top_level.txt
git_utils_py-0.0.7.dist-info/RECORD
