Metadata-Version: 2.1
Name: git-utils-py
Version: 0.0.7
Summary: Library to download files from gitlab
Home-page: https://bitbucket.org/informaticaljd
Author: Juan José Macanás Beteta
Author-email: juanjo.macanas@gmail.com
License: MIT
Platform: UNKNOWN
Classifier: Natural Language :: English
Classifier: Operating System :: Microsoft :: Windows
Classifier: Programming Language :: Python
Classifier: Programming Language :: Python :: 3
Classifier: Programming Language :: Python :: 3.7
Classifier: Programming Language :: Python :: 3.8
Classifier: Programming Language :: Python :: 3.9
Classifier: Programming Language :: Python :: 3.10
Requires-Python: >=3.7.0
Requires-Dist: python-gitlab
